FW4py/__init__.py
FW4py-0.0.6.dist-info/LICENSE.txt
FW4py-0.0.6.dist-info/METADATA
FW4py-0.0.6.dist-info/WHEEL
FW4py-0.0.6.dist-info/top_level.txt
FW4py-0.0.6.dist-info/RECORD
